{"entradas":[{"posicion":1,"universidad":"Lomonosov Moscow State University "},{"posicion":2,"universidad":"Saint Petersburg State University "},{"posicion":3,"universidad":"National Research University Higher School of Economics "},{"posicion":4,"universidad":"National Nuclear Research University (Moscow State Engineering Physics Institute) "},{"posicion":5,"universidad":"Peter the Great St.Petersburg Polytechnic University "},{"posicion":6,"universidad":"Tomsk State University "},{"posicion":7,"universidad":"Moscow Institute of Physics and Technology "},{"posicion":8,"universidad":"Kazan (Volga Region) Federal University "},{"posicion":9,"universidad":"Novosibirsk State University "},{"posicion":10,"universidad":"Ural Federal University "},{"posicion":11,"universidad":"ITMO University "},{"posicion":12,"universidad":"Nizhny Novgorod State University "},{"posicion":13,"universidad":"Southern Federal University (Rostov State University) "},{"posicion":14,"universidad":"Saratov State University "},{"posicion":15,"universidad":"Far Eastern Federal University "},{"posicion":16,"universidad":"National University of Science & Technology MISIS (Moscow Institute of Steel and Alloys) "},{"posicion":17,"universidad":"Siberian Federal University "},{"posicion":18,"universidad":"Samara National Research University "},{"posicion":19,"universidad":"Bauman Moscow State Technical University "},{"posicion":20,"universidad":" Friendship University of Russia "},{"posicion":21,"universidad":"Tomsk Polytechnic University "},{"posicion":22,"universidad":"Belgorod State University "},{"posicion":23,"universidad":"Novosibirsk State Technical University "},{"posicion":24,"universidad":"Russian University of Economics G V Plekhanov "},{"posicion":25,"universidad":"South Ural State University "},{"posicion":26,"universidad":"Voronezh State University "},{"posicion":27,"universidad":"Financial University under the Government of the Russian Federation "},{"posicion":28,"universidad":"North Eastern Federal University MK Ammosova (Yakutsk State University) "},{"posicion":29,"universidad":"Moscow Power Engineering Institute "},{"posicion":30,"universidad":"Russian State Social University "},{"posicion":31,"universidad":"Altai State University "},{"posicion":32,"universidad":"Moscow State University of Civil Engineering "},{"posicion":33,"universidad":"Tomsk State Pedagogical University "},{"posicion":34,"universidad":"Udmurt State University "},{"posicion":35,"universidad":"Chelyabinsk State University "},{"posicion":36,"universidad":"Mordovia State University "},{"posicion":37,"universidad":"Bashkir State University "},{"posicion":38,"universidad":"Tyumen State University "},{"posicion":39,"universidad":"Moscow Aviation Institute National Research University "},{"posicion":40,"universidad":"Tomsk State University of Control Systems and Radioelectronics "},{"posicion":41,"universidad":"Petrozavodsk State University "},{"posicion":42,"universidad":"Russian State Medical University "},{"posicion":43,"universidad":"Irkutsk State University "},{"posicion":44,"universidad":"Perm State University "},{"posicion":45,"universidad":"Gubkin Russian State University of Oil and Gas "},{"posicion":46,"universidad":"Ulyanovsk State University "},{"posicion":47,"universidad":"Kuban State University "},{"posicion":48,"universidad":"Moscow State Institute of International Relations "},{"posicion":49,"universidad":"Perm State Technical University "},{"posicion":50,"universidad":"Moscow Technological University "},{"posicion":51,"universidad":"Yuri Gagarin State Technical University of Saratov "},{"posicion":52,"universidad":"Volgograd State Technical University "},{"posicion":53,"universidad":"Immanuel Kant State University of Russia (Kaliningrad State University) "},{"posicion":54,"universidad":"Penza State University "},{"posicion":55,"universidad":"Northern (Arctic) Federal University (Arkhangelsk State Technical University) "},{"posicion":56,"universidad":"Kemerovo State University "},{"posicion":57,"universidad":"Siberian State Aerospace University "},{"posicion":58,"universidad":"Irkutsk State Technical University "},{"posicion":59,"universidad":"Yaroslavl State University "},{"posicion":60,"universidad":"Don State Technical University "},{"posicion":61,"universidad":"Russian State Pedagogical University AI Herzen (Gertsenovsky University) "},{"posicion":62,"universidad":"Mendeleev University of Chemical Technology of Russia "},{"posicion":63,"universidad":"Southwestern State University Kursk "},{"posicion":64,"universidad":"Saint Petersburg State Electrotechnical University "},{"posicion":65,"universidad":"New Economic School "},{"posicion":66,"universidad":"Orenburg State University "},{"posicion":67,"universidad":"Tambov State Technical University "},{"posicion":68,"universidad":"Moscow State Technological University Stankin "},{"posicion":69,"universidad":"Volgograd State University "},{"posicion":70,"universidad":"Russian State Hydrometeorological University "},{"posicion":71,"universidad":"Omsk State Technical University "},{"posicion":72,"universidad":"Saint Petersburg Mining University "},{"posicion":73,"universidad":"Belgorod State Technological University VG Shukhov "},{"posicion":74,"universidad":"Tyumen Industrial University "},{"posicion":75,"universidad":"Moscow State University of Medicine and Dentistry "},{"posicion":76,"universidad":"Magnitogorsk State Technical University "},{"posicion":77,"universidad":"Russian State Vocational Pedagogical University "},{"posicion":78,"universidad":"Syktyvkar State University "},{"posicion":79,"universidad":"Mari State University "},{"posicion":80,"universidad":"Nizhny Novgorod State Technical University "},{"posicion":81,"universidad":"Vyatka State University "},{"posicion":82,"universidad":"Ulyanovsk State Technical University "},{"posicion":83,"universidad":"Siberian State Medical Academy "},{"posicion":84,"universidad":"North-Caucasus Federal University (Stavropol State University) "},{"posicion":85,"universidad":"Ivanovo State University of Chemistry and Technology "},{"posicion":86,"universidad":"Moscow Institute of Electronic Technology "},{"posicion":87,"universidad":"Moscow State Regional University "},{"posicion":88,"universidad":"Ural State Economical University "},{"posicion":89,"universidad":"Saint Petersburg State Pavlov Medical University "},{"posicion":90,"universidad":"Izhevsk State Technical University "},{"posicion":91,"universidad":"Russian Presidential Academy of National Economy and Public Administration "},{"posicion":92,"universidad":"(1) Russian State University for the Humanities "},{"posicion":93,"universidad":"Moscow State University of Railway Transport "},{"posicion":94,"universidad":"(1) Ufa State Petroleum Technological University "},{"posicion":95,"universidad":"Ural State Pedagogical University "},{"posicion":96,"universidad":"Dubna International University for Nature Society and Man "},{"posicion":97,"universidad":"Omsk State University "},{"posicion":98,"universidad":"Moscow Pedagogical State University "},{"posicion":99,"universidad":"Saint Petersburg State Technological Institute (Technical University) "},{"posicion":100,"universidad":"Samara State Medical University "}]}